{
  "description": "PhotoMedGemma photonic chip vs real MedGemma layer-0 attention",
  "projections": [
    {
      "proj": "q_proj",
      "weight_shape": [
        2048,
        2560
      ],
      "rank_compiled": 64,
      "full_rank": 2048,
      "energy_retained_rank64": 0.2877784138205564,
      "energy_retained_full": 1.0,
      "n_mzis_per_mesh_rank64": 2016,
      "n_mzis_per_mesh_full": 2096128,
      "compilation_error_U": 7.020699101161384e-15,
      "compilation_error_Vh": 7.848641965651407e-15,
      "n_images": 5,
      "clements_self_consistency": 6.063894578834076e-16,
      "mean_chip_fidelity": 1.0803194237115614e-15,
      "mean_rank64_svd_error": 0.18592794825298273,
      "mean_fullrank_svd_error": 1.8827290336033418e-15,
      "mean_quantization_error": 0.0017176693396591155,
      "pass_chip_fidelity": true,
      "per_image": [
        {
          "stem": "10011_1031443799",
          "n_tokens_tested": 1,
          "mean_chip_fidelity": 6.060939056195201e-16,
          "mean_rank64_svd_error": 0.28179329700226646,
          "mean_fullrank_svd_error": 1.9917601001515286e-15,
          "mean_quantization_error": 0.0018468644997259303,
          "pass_chip_fidelity": true
        },
        {
          "stem": "10025_893612858",
          "n_tokens_tested": 1,
          "mean_chip_fidelity": 1.10465812415215e-15,
          "mean_rank64_svd_error": 0.148536781411564,
          "mean_fullrank_svd_error": 1.857135288338135e-15,
          "mean_quantization_error": 0.0016133114848856575,
          "pass_chip_fidelity": true
        },
        {
          "stem": "10042_102733848",
          "n_tokens_tested": 1,
          "mean_chip_fidelity": 1.481528840481837e-15,
          "mean_rank64_svd_error": 0.20223610002795514,
          "mean_fullrank_svd_error": 1.8504792028507767e-15,
          "mean_quantization_error": 0.001901547743912675,
          "pass_chip_fidelity": true
        },
        {
          "stem": "10042_1648588715",
          "n_tokens_tested": 1,
          "mean_chip_fidelity": 1.10465812415215e-15,
          "mean_rank64_svd_error": 0.148536781411564,
          "mean_fullrank_svd_error": 1.857135288338135e-15,
          "mean_quantization_error": 0.0016133114848856575,
          "pass_chip_fidelity": true
        },
        {
          "stem": "10042_495770405",
          "n_tokens_tested": 1,
          "mean_chip_fidelity": 1.10465812415215e-15,
          "mean_rank64_svd_error": 0.148536781411564,
          "mean_fullrank_svd_error": 1.857135288338135e-15,
          "mean_quantization_error": 0.0016133114848856575,
          "pass_chip_fidelity": true
        }
      ]
    },
    {
      "proj": "k_proj",
      "weight_shape": [
        1024,
        2560
      ],
      "rank_compiled": 64,
      "full_rank": 1024,
      "energy_retained_rank64": 0.27314830584700267,
      "energy_retained_full": 1.0,
      "n_mzis_per_mesh_rank64": 2016,
      "n_mzis_per_mesh_full": 523776,
      "compilation_error_U": 5.190900666423578e-15,
      "compilation_error_Vh": 7.89769502895788e-15,
      "n_images": 5,
      "clements_self_consistency": 5.95128991709203e-16,
      "mean_chip_fidelity": 1.2174372986101677e-15,
      "mean_rank64_svd_error": 0.24923176787938064,
      "mean_fullrank_svd_error": 1.9318027519715897e-15,
      "mean_quantization_error": 0.0018679186472071515,
      "pass_chip_fidelity": true,
      "per_image": [
        {
          "stem": "10011_1031443799",
          "n_tokens_tested": 1,
          "mean_chip_fidelity": 8.89475535249117e-16,
          "mean_rank64_svd_error": 0.3764040482823515,
          "mean_fullrank_svd_error": 2.280329335532358e-15,
          "mean_quantization_error": 0.0020470159167135372,
          "pass_chip_fidelity": true
        },
        {
          "stem": "10025_893612858",
          "n_tokens_tested": 1,
          "mean_chip_fidelity": 1.5074623988583185e-15,
          "mean_rank64_svd_error": 0.21599893113231447,
          "mean_fullrank_svd_error": 1.8454100681777216e-15,
          "mean_quantization_error": 0.0018503724699010324,
          "pass_chip_fidelity": true
        },
        {
          "stem": "10042_102733848",
          "n_tokens_tested": 1,
          "mean_chip_fidelity": 6.753237612267653e-16,
          "mean_rank64_svd_error": 0.2217579977176082,
          "mean_fullrank_svd_error": 1.8424542197924272e-15,
          "mean_quantization_error": 0.0017414599096191225,
          "pass_chip_fidelity": true
        },
        {
          "stem": "10042_1648588715",
          "n_tokens_tested": 1,
          "mean_chip_fidelity": 1.5074623988583185e-15,
          "mean_rank64_svd_error": 0.21599893113231447,
          "mean_fullrank_svd_error": 1.8454100681777216e-15,
          "mean_quantization_error": 0.0018503724699010324,
          "pass_chip_fidelity": true
        },
        {
          "stem": "10042_495770405",
          "n_tokens_tested": 1,
          "mean_chip_fidelity": 1.5074623988583185e-15,
          "mean_rank64_svd_error": 0.21599893113231447,
          "mean_fullrank_svd_error": 1.8454100681777216e-15,
          "mean_quantization_error": 0.0018503724699010324,
          "pass_chip_fidelity": true
        }
      ]
    },
    {
      "proj": "v_proj",
      "weight_shape": [
        1024,
        2560
      ],
      "rank_compiled": 64,
      "full_rank": 1024,
      "energy_retained_rank64": 0.2864597237270176,
      "energy_retained_full": 1.0,
      "n_mzis_per_mesh_rank64": 2016,
      "n_mzis_per_mesh_full": 523776,
      "compilation_error_U": 5.237103862775368e-15,
      "compilation_error_Vh": 7.985801448495927e-15,
      "n_images": 5,
      "clements_self_consistency": 6.442343541099381e-16,
      "mean_chip_fidelity": 8.086726982428809e-16,
      "mean_rank64_svd_error": 0.6689891760006863,
      "mean_fullrank_svd_error": 3.128523982652852e-15,
      "mean_quantization_error": 0.002209062206238804,
      "pass_chip_fidelity": true,
      "per_image": [
        {
          "stem": "10011_1031443799",
          "n_tokens_tested": 1,
          "mean_chip_fidelity": 1.173964407728903e-15,
          "mean_rank64_svd_error": 0.696280938442096,
          "mean_fullrank_svd_error": 3.308577250329898e-15,
          "mean_quantization_error": 0.0026549766920291873,
          "pass_chip_fidelity": true
        },
        {
          "stem": "10025_893612858",
          "n_tokens_tested": 1,
          "mean_chip_fidelity": 7.197560656109682e-16,
          "mean_rank64_svd_error": 0.6356401653949374,
          "mean_fullrank_svd_error": 3.004644784856931e-15,
          "mean_quantization_error": 0.0020945794285010654,
          "pass_chip_fidelity": true
        },
        {
          "stem": "10042_102733848",
          "n_tokens_tested": 1,
          "mean_chip_fidelity": 7.101308866525964e-16,
          "mean_rank64_svd_error": 0.7417444453765235,
          "mean_fullrank_svd_error": 3.3201083083635673e-15,
          "mean_quantization_error": 0.0021065960536616386,
          "pass_chip_fidelity": true
        },
        {
          "stem": "10042_1648588715",
          "n_tokens_tested": 1,
          "mean_chip_fidelity": 7.197560656109682e-16,
          "mean_rank64_svd_error": 0.6356401653949374,
          "mean_fullrank_svd_error": 3.004644784856931e-15,
          "mean_quantization_error": 0.0020945794285010654,
          "pass_chip_fidelity": true
        },
        {
          "stem": "10042_495770405",
          "n_tokens_tested": 1,
          "mean_chip_fidelity": 7.197560656109682e-16,
          "mean_rank64_svd_error": 0.6356401653949374,
          "mean_fullrank_svd_error": 3.004644784856931e-15,
          "mean_quantization_error": 0.0020945794285010654,
          "pass_chip_fidelity": true
        }
      ]
    },
    {
      "proj": "o_proj",
      "weight_shape": [
        2560,
        2048
      ],
      "rank_compiled": 64,
      "full_rank": 2048,
      "energy_retained_rank64": 0.23459721465916444,
      "energy_retained_full": 1.0,
      "n_mzis_per_mesh_rank64": 2016,
      "n_mzis_per_mesh_full": 2096128,
      "compilation_error_U": 7.752522646059788e-15,
      "compilation_error_Vh": 6.923153833090575e-15,
      "n_images": 5,
      "clements_self_consistency": 6.771734783337284e-16,
      "mean_chip_fidelity": 1.0727861568385004e-15,
      "mean_rank64_svd_error": 0.3105600153979211,
      "mean_fullrank_svd_error": 2.3746220624895464e-15,
      "mean_quantization_error": 0.0019701403860507777,
      "pass_chip_fidelity": true,
      "per_image": [
        {
          "stem": "10011_1031443799",
          "n_tokens_tested": 1,
          "mean_chip_fidelity": 1.1558006228318245e-15,
          "mean_rank64_svd_error": 0.2374466334691545,
          "mean_fullrank_svd_error": 2.2529600136208363e-15,
          "mean_quantization_error": 0.0017799295268645973,
          "pass_chip_fidelity": true
        },
        {
          "stem": "10025_893612858",
          "n_tokens_tested": 1,
          "mean_chip_fidelity": 1.2013750824271896e-15,
          "mean_rank64_svd_error": 0.3374411744933562,
          "mean_fullrank_svd_error": 2.0687668368348168e-15,
          "mean_quantization_error": 0.002193082890610561,
          "pass_chip_fidelity": true
        },
        {
          "stem": "10042_102733848",
          "n_tokens_tested": 1,
          "mean_chip_fidelity": 9.514448916538655e-16,
          "mean_rank64_svd_error": 0.28823689613858033,
          "mean_fullrank_svd_error": 2.6299291580312385e-15,
          "mean_quantization_error": 0.0017333040335917073,
          "pass_chip_fidelity": true
        },
        {
          "stem": "10042_1648588715",
          "n_tokens_tested": 1,
          "mean_chip_fidelity": 1.203713957266789e-15,
          "mean_rank64_svd_error": 0.35481336470227876,
          "mean_fullrank_svd_error": 2.434270186379379e-15,
          "mean_quantization_error": 0.0021968600727073563,
          "pass_chip_fidelity": true
        },
        {
          "stem": "10042_495770405",
          "n_tokens_tested": 1,
          "mean_chip_fidelity": 8.51596230012834e-16,
          "mean_rank64_svd_error": 0.3348620081862357,
          "mean_fullrank_svd_error": 2.48718411758146e-15,
          "mean_quantization_error": 0.0019475254064796684,
          "pass_chip_fidelity": true
        }
      ]
    }
  ]
}