{
  "format": "PhotoMedGemma JSON Manifest v1.0",
  "model": "google/medgemma-4b-it",
  "n_layers": 7,
  "total_mzis": 120096,
  "layers": [
    {
      "name": "model.layers.0.self_attn.q_proj.weight",
      "component": "language_model",
      "projection_type": "q_proj",
      "transformer_layer_idx": 0,
      "rank": 63,
      "input_dim": 64,
      "output_dim": 64,
      "n_mzis_Vh": 2016,
      "n_mzis_U": 2016,
      "chip_id_Vh": 0,
      "chip_id_U": 0,
      "reconstruction_error_svd": 7.160726860130142e-06,
      "reconstruction_error_clements_U": 2.0719638686451483e-15,
      "reconstruction_error_clements_Vh": 1.9751357457507127e-15
    },
    {
      "name": "model.layers.0.self_attn.k_proj.weight",
      "component": "language_model",
      "projection_type": "k_proj",
      "transformer_layer_idx": 0,
      "rank": 63,
      "input_dim": 64,
      "output_dim": 64,
      "n_mzis_Vh": 2016,
      "n_mzis_U": 2016,
      "chip_id_Vh": 1,
      "chip_id_U": 1,
      "reconstruction_error_svd": 5.267140561419053e-06,
      "reconstruction_error_clements_U": 1.907100930755808e-15,
      "reconstruction_error_clements_Vh": 2.045086007527808e-15
    },
    {
      "name": "model.layers.0.self_attn.v_proj.weight",
      "component": "language_model",
      "projection_type": "v_proj",
      "transformer_layer_idx": 0,
      "rank": 63,
      "input_dim": 64,
      "output_dim": 64,
      "n_mzis_Vh": 2016,
      "n_mzis_U": 2016,
      "chip_id_Vh": 2,
      "chip_id_U": 2,
      "reconstruction_error_svd": 1.9010108040102468e-05,
      "reconstruction_error_clements_U": 2.1167083116647576e-15,
      "reconstruction_error_clements_Vh": 2.2125939180218492e-15
    },
    {
      "name": "model.layers.0.self_attn.o_proj.weight",
      "component": "language_model",
      "projection_type": "o_proj",
      "transformer_layer_idx": 0,
      "rank": 63,
      "input_dim": 64,
      "output_dim": 64,
      "n_mzis_Vh": 2016,
      "n_mzis_U": 2016,
      "chip_id_Vh": 3,
      "chip_id_U": 3,
      "reconstruction_error_svd": 3.557249360540095e-06,
      "reconstruction_error_clements_U": 2.1089062374598573e-15,
      "reconstruction_error_clements_Vh": 2.122853422317125e-15
    },
    {
      "name": "model.layers.0.mlp.gate_proj.weight",
      "component": "language_model",
      "projection_type": "gate",
      "transformer_layer_idx": 0,
      "rank": 63,
      "input_dim": 64,
      "output_dim": 256,
      "n_mzis_Vh": 2016,
      "n_mzis_U": 32640,
      "chip_id_Vh": 4,
      "chip_id_U": 5,
      "reconstruction_error_svd": 0.0004951106839696991,
      "reconstruction_error_clements_U": 3.286474465755218e-15,
      "reconstruction_error_clements_Vh": 2.092769763107024e-15
    },
    {
      "name": "model.layers.0.mlp.up_proj.weight",
      "component": "language_model",
      "projection_type": "up",
      "transformer_layer_idx": 0,
      "rank": 63,
      "input_dim": 64,
      "output_dim": 256,
      "n_mzis_Vh": 2016,
      "n_mzis_U": 32640,
      "chip_id_Vh": 6,
      "chip_id_U": 7,
      "reconstruction_error_svd": 0.00044645777546765064,
      "reconstruction_error_clements_U": 3.186465055958812e-15,
      "reconstruction_error_clements_Vh": 2.0862715239214224e-15
    },
    {
      "name": "model.layers.0.mlp.down_proj.weight",
      "component": "language_model",
      "projection_type": "down",
      "transformer_layer_idx": 0,
      "rank": 63,
      "input_dim": 256,
      "output_dim": 64,
      "n_mzis_Vh": 32640,
      "n_mzis_U": 2016,
      "chip_id_Vh": 8,
      "chip_id_U": 9,
      "reconstruction_error_svd": 0.0004996732591771868,
      "reconstruction_error_clements_U": 2.1324723770908905e-15,
      "reconstruction_error_clements_Vh": 3.2131345732239335e-15
    }
  ]
}